{"id":"38275082","premium":false,"billing_type":{"id":"standard","name":"Стандарт"},"relations":[],"name":"Data engineer","insider_interview":null,"response_letter_required":false,"area":{"id":"1","name":"Москва","url":"https://api.hh.ru/areas/1?host=hh.ru"},"salary":null,"type":{"id":"open","name":"Открытая"},"address":{"city":null,"street":null,"building":null,"description":null,"lat":null,"lng":null,"raw":null,"metro":{"station_name":"Кутузовская","line_name":"Филевская","station_id":"4.73","line_id":"4","lat":55.740544,"lng":37.5341},"metro_stations":[{"station_name":"Кутузовская","line_name":"Филевская","station_id":"4.73","line_id":"4","lat":55.740544,"lng":37.5341},{"station_name":"Кутузовская","line_name":"МЦК","station_id":"95.536","line_id":"95","lat":55.740833,"lng":37.533333},{"station_name":"Парк Победы","line_name":"Арбатско-Покровская","station_id":"3.173","line_id":"3","lat":55.735679,"lng":37.516865},{"station_name":"Студенческая","line_name":"Филевская","station_id":"4.136","line_id":"4","lat":55.738761,"lng":37.54842}]},"allow_messages":true,"site":{"id":"hh","name":"hh.ru"},"experience":{"id":"between3And6","name":"От 3 до 6 лет"},"schedule":{"id":"fullDay","name":"Полный день"},"employment":{"id":"full","name":"Полная занятость"},"department":null,"contacts":null,"description":"<p><strong>Что такое СберЗвук?</strong></p> <p>Мультиплатформенный встраиваемый аудиосервис, который будет сопровождать человека в течение всего дня, где бы он не находился и что бы он ни делал, бесшовно перетекая вслед за ним с платформы на платформу, с устройства на устройство.</p> <p><strong>Наша миссия</strong></p> <p>Помочь современному человеку проживать каждый час своей жизни с максимальной пользой. На утренней пробежке, мы помогаем держать темп, в дороге мы расширяем его кругозор с помощью подкастов, а вечером объединяем семью вокруг аудиоспектакля.</p> <p><strong>Наша цель</strong></p> <p>Собрать в СберЗвуке весь контент, который можно потреблять аудиально, и цитатное видео, чтобы занять максимум внимания пользователя в те продолжительные моменты жизни, когда он не находится непосредственно перед экраном.</p> <p>Мы ищем специалиста, которому важно видеть влияние своей работы на продукт компании.</p> <p> </p> <p><strong>Чем тебе предстоит заниматься:</strong></p> <ul> <li> <p>Созданием инструментов для анализа и исследования поведения пользователей, разработанных совместно с аналитиками.</p> </li> <li> <p>Обеспечением надежности и развитием инфраструктуры обработки данных.</p> </li> </ul> <p><strong>С какими технологиями придется иметь дело:</strong></p> <ul> <li> <p>Hadoop (Hive, HDFS), Kafka, Spark, Docker, Nomad, Luigi.</p> </li> <li> <p>PostgreSQL, Clickhouse.</p> </li> <li> <p>Python, Java.</p> </li> </ul> <p><strong>Наш будущий коллега выглядит так (в нашем идеальном мире):</strong></p> <ul> <li> <p>Не менее 2-х лет опыта работы на позиции Software Engineer и использует python;</p> </li> <li> <p>Знание базовых алгоритмов и структур данных и умение их применять.</p> </li> <li> <p>Понимание принципов работы распределенных систем.</p> </li> <li> <p>Знание операционных систем (Linux).</p> </li> <li> <p>Умение с нуля продумывать архитектуру программных решений и быстро создавать прототип.</p> </li> <li> <p>Уверенное владение любым современным языком программирования.</p> </li> <li> <p>Навыки системного подхода к поиску проблем/багов и их исправления.</p> </li> <li> <p>Опыт работы с Hadoop или аналогичными системами для обработки больших объемов данных.</p> </li> <li> <p>Желание и умение быстро разбираться с новыми инструментами, оценивать их применимость для решения поставленных задач.</p> </li> </ul> <p><strong>Что мы ценим в кандидатах:</strong></p> <ul> <li>Умение работать в команде.</li> <li>Инициативность в улучшении работы сервиса.</li> <li>Готовность учиться и учить, помогать коллегам в решении задач.</li> <li>Выбор работы происходит по следующим критериям: продукт, задачи, команда.</li> <li>Отстаивание своей точки зрения, уважая также мнения коллег.</li> <li>Понимание особенностей работы в небольших компаниях.</li> <li>Поиск команды, совпадающей с ним по ценностям.</li> </ul> <p><strong>Работа должна быть в удовольствие, поэтому ты получаешь:</strong></p> <ul> <li>Интересные и разноплановые задачи.</li> <li>Место в современном офисе, разделенном на зоны: есть рабочий опенспейс, чилл-зона, кухня, зоны для игр и переговорки. В общем, каждый точно найдет свой угол.</li> <li>Удобное расположение офиса: между м. Кутузовская и м.Парк Победы</li> <li>Работа в офисе, но с комфортным рабочим графиком. Иногда (именно иногда) можно работать из дома (например, если у тебя творческое настроение, или, может, бытовые или семейные вопросы – мы не против).</li> <li>Ноут и большой экран на большом столе и возможность работать не за ним, а, например, на пуфиках в чилл-зоне.</li> </ul> <p><strong>Напишите нам если</strong></p> <ul> <li> <p>Вы разделяете наши цели</p> </li> <li> <p>Не боитесь работы на конкурентном рынке</p> </li> <li> <p>И при этом вы настоящий трудоголик, а работа может приносить вам подлинное удовольствие</p> </li> <li> <p>Хотите работать в продукте, которым пользуются миллионы</p> </li> <li> <p>Хотите работать в компании-лидере рынка</p> </li> <li> <p>Умеете и любите работать в команде, где у каждого есть своя роль, но цели у всех общие</p> </li> <li> <p>Умеете мыслить стратегически, в масштабе нескольких лет</p> </li> <li> <p>Умеете работать самостоятельно и принимать ответственность свои за решения</p> </li> <li> <p>Вы проактивны и обладаете высоким уровнем самоорганизации: легко составляете таймлайны, планы и идете по ним</p> </li> <li> <p>Можете аргументированно отстаивать свою точку зрения</p> </li> <li> <p>Оперируете логикой и реалиями рынка</p> </li> <li> <p>Работаете быстро и решаете задачи в срок</p> </li> <li> <p>Легко адаптируетесь к переменчивым целям и изменениям в стратегии</p> </li> <li> <p>Можете одновременно вести несколько проектов или крупных задач</p> </li> </ul> <p>Подробнее про нас и нашу команду смотрите на https://jobs.sber-zvuk.com</p>","branded_description":null,"vacancy_constructor_template":null,"key_skills":[{"name":"Python"},{"name":"PostgreSQL"},{"name":"Redis"},{"name":"Docker"},{"name":"Flask"},{"name":"Nomad"}],"accept_handicapped":false,"accept_kids":false,"archived":false,"response_url":null,"specializations":[{"id":"1.221","name":"Программирование, Разработка","profarea_id":"1","profarea_name":"Информационные технологии, интернет, телеком"},{"id":"1.82","name":"Инженер","profarea_id":"1","profarea_name":"Информационные технологии, интернет, телеком"}],"code":null,"hidden":false,"quick_responses_allowed":false,"driver_license_types":[],"accept_incomplete_resumes":false,"employer":{"id":"1829949","name":"СберЗвук","url":"https://api.hh.ru/employers/1829949?host=hh.ru","alternate_url":"https://hh.ru/employer/1829949","logo_urls":{"original":"https://hhcdn.ru/employer-logo-original/777454.png","240":"https://hhcdn.ru/employer-logo/3550708.png","90":"https://hhcdn.ru/employer-logo/3550707.png"},"vacancies_url":"https://api.hh.ru/vacancies?employer_id=1829949&host=hh.ru","trusted":true},"published_at":"2020-12-01T17:38:12+0300","created_at":"2020-12-01T17:38:12+0300","negotiations_url":null,"suitable_resumes_url":null,"apply_alternate_url":"https://hh.ru/applicant/vacancy_response?vacancyId=38275082","has_test":false,"test":null,"alternate_url":"https://hh.ru/vacancy/38275082","working_days":[],"working_time_intervals":[],"working_time_modes":[],"accept_temporary":false}