{"id":"40355790","premium":false,"billing_type":{"id":"standard_plus","name":"Стандарт плюс"},"relations":[],"name":"Data Team QA Automation Engineer","insider_interview":null,"response_letter_required":false,"area":{"id":"1002","name":"Минск","url":"https://api.hh.ru/areas/1002?host=hh.ru"},"salary":null,"type":{"id":"open","name":"Открытая"},"address":null,"allow_messages":true,"site":{"id":"hh","name":"hh.ru"},"experience":{"id":"between3And6","name":"От 3 до 6 лет"},"schedule":{"id":"fullDay","name":"Полный день"},"employment":{"id":"full","name":"Полная занятость"},"department":null,"contacts":null,"description":"<p><strong>Playtika</strong> is a multiplatform games developer, it is the top 3 grossing Facebook developer and the top 10 grossing developer on iOS &amp; Android. Playtika’s passion is to immerse players into a thrilling entertainment experience results in 200 million installations, 6 million daily active users and 20 million monthly active users. 3500+ employees work &amp; play in Playtika’s offices in: Israel (headquarters), US, Canada, Belarus, Argentina, Japan, Ukraine &amp; Romania.</p> <p>We are looking for a <strong>QA Automation Engineer for Data Team </strong>to work with on casual games studios in Minsk office!</p> <p>If you are interested in working with talented and passionate teammates and becoming a driving force for the evolution of Big Data and Machine Learning systems, then Playtika Minsk will be the right fit for you</p> <p><strong>Responsibilities include:</strong></p> <ul> <li>Design and implementation of the Test Automation Framework;</li> <li>Establishment of test scripts, test suites and libraries for the automated test system;</li> <li>Maintenance of the fully integrated test automation for Big Data pipeline;</li> <li>Analysis of product quality related data and develop automation projects from quality improvement to actively ensure product quality;</li> <li>Work closely with the different departments, technical &amp; business;</li> <li>Identify new approaches to automation, and new tools that can help automate manual tests.</li> </ul> <p><strong>Desired Skills and Experience:</strong></p> <ul> <li>Experience in creating QA Automation framework from scratch;</li> <li>Good Java skills;</li> <li>Experience in CI/CD;</li> <li>SQL knowledge (more than basic level) and experience in working with DBs;</li> <li>Understanding of test types/levels, testing approaches (TDD, BDD);</li> <li>Experience in REST API testing;</li> <li>Be comfortable with Linux command line;</li> <li>Strong analytical and troubleshooting skills.</li> </ul> <p><strong>Preferred qualifications:</strong></p> <ul> <li>Experience in Big Data tools (Kafka, HDFS, Spark, etc.);</li> <li>Experience in Spring services;</li> <li>Experience in k8s, Docker;</li> <li>Knowledge of Python.</li> </ul> <p><strong>We offer:</strong></p> <ul> <li>Competitive salary, performance-based bonuses and flexible working hours;</li> <li>Social package, including gym membership compensation, medical insurance with dental coverage;</li> <li>Paid vacation and sick leaves;</li> <li>Training programs, certifications, conferences including international events;</li> <li>Corporate English classes;</li> <li>Referral program;</li> <li>Corporate celebrations, team buildings, and fun activities;</li> <li>Free meals twice a day, refreshments, happy hours;</li> <li>Technical library with option to order books;</li> <li>Coaching and reviews to support your career development;</li> <li>Working for one of the top social gaming companies in the world.</li> </ul> <p><strong>Come play with us!</strong></p>","branded_description":null,"vacancy_constructor_template":null,"key_skills":[{"name":"Java"},{"name":"Python"},{"name":"SQL"},{"name":"REST"},{"name":"Linux"}],"accept_handicapped":false,"accept_kids":false,"archived":false,"response_url":null,"specializations":[{"id":"1.475","name":"Игровое ПО","profarea_id":"1","profarea_name":"Информационные технологии, интернет, телеком"},{"id":"1.117","name":"Тестирование","profarea_id":"1","profarea_name":"Информационные технологии, интернет, телеком"}],"code":null,"hidden":false,"quick_responses_allowed":false,"driver_license_types":[],"accept_incomplete_resumes":false,"employer":{"id":"1105861","name":"Плэйтика Бел, ИООО","url":"https://api.hh.ru/employers/1105861?host=hh.ru","alternate_url":"https://hh.ru/employer/1105861","logo_urls":{"original":"https://hhcdn.ru/employer-logo-original/241869.jpg","90":"https://hhcdn.ru/employer-logo/1410153.jpeg","240":"https://hhcdn.ru/employer-logo/1410154.jpeg"},"vacancies_url":"https://api.hh.ru/vacancies?employer_id=1105861&host=hh.ru","trusted":true},"published_at":"2020-12-05T17:18:20+0300","created_at":"2020-12-05T17:18:20+0300","negotiations_url":null,"suitable_resumes_url":null,"apply_alternate_url":"https://hh.ru/applicant/vacancy_response?vacancyId=40355790","has_test":false,"test":null,"alternate_url":"https://hh.ru/vacancy/40355790","working_days":[],"working_time_intervals":[],"working_time_modes":[],"accept_temporary":false}