{"id":"40700178","premium":false,"billing_type":{"id":"standard_plus","name":"Стандарт плюс"},"relations":[],"name":"Data Engineer","insider_interview":null,"response_letter_required":false,"area":{"id":"88","name":"Казань","url":"https://api.hh.ru/areas/88?host=hh.ru"},"salary":null,"type":{"id":"open","name":"Открытая"},"address":null,"allow_messages":true,"site":{"id":"hh","name":"hh.ru"},"experience":{"id":"between3And6","name":"От 3 до 6 лет"},"schedule":{"id":"fullDay","name":"Полный день"},"employment":{"id":"full","name":"Полная занятость"},"department":null,"contacts":null,"description":"<p><strong>Требования: </strong></p> <p> </p> <p>- 5+ года опыта работы в качестве Python разработчика.</p> <p>- Опыт работы с такими инструментами разработчика, как Git, Gitflow.</p> <p>- Знание и понимание реляционных баз данных и no-SQL БД.</p> <p>- Опыт разработки серверного API.</p> <p>- Опыт использования и применения современных паттернов разработки.</p> <p>- Английский: intermediate+</p> <p><strong>Будет плюсом:</strong></p> <p>- Опыт работы с Big Data Hive, Spark, Apache AirFlow.</p> <p>- Опыт работы с Kafka, Maven, Jenkins, Docker.</p> <p>- Знание классического хранилища данных.</p> <p>- Представление о машинном обучении.</p> <p>- Опыт работы на Java или Scala.</p> <p><strong>Обязанности: </strong></p> <p> </p> <p>- Разрабатывать приложения с низкой задержкой, высокой доступностью и производительностью.</p> <p>- Проектировать и реализовывать data pipelines.</p> <p>- Писать автотесты, участвовать в code reviews.</p> <p>- Писать и оптимизировать сложные запросы к базе данных для построения аналитических отчетов.</p>","branded_description":null,"vacancy_constructor_template":null,"key_skills":[{"name":"Python"}],"accept_handicapped":false,"accept_kids":false,"archived":false,"response_url":null,"specializations":[{"id":"1.221","name":"Программирование, Разработка","profarea_id":"1","profarea_name":"Информационные технологии, интернет, телеком"}],"code":null,"hidden":false,"quick_responses_allowed":false,"driver_license_types":[],"accept_incomplete_resumes":false,"employer":{"id":"841622","name":"Provectus","url":"https://api.hh.ru/employers/841622?host=hh.ru","alternate_url":"https://hh.ru/employer/841622","logo_urls":{"original":"https://hhcdn.ru/employer-logo-original/248283.png","90":"https://hhcdn.ru/employer-logo/1435805.png","240":"https://hhcdn.ru/employer-logo/1435806.png"},"vacancies_url":"https://api.hh.ru/vacancies?employer_id=841622&host=hh.ru","trusted":true},"published_at":"2020-12-03T10:52:34+0300","created_at":"2020-12-03T10:52:34+0300","negotiations_url":null,"suitable_resumes_url":null,"apply_alternate_url":"https://hh.ru/applicant/vacancy_response?vacancyId=40700178","has_test":false,"test":null,"alternate_url":"https://hh.ru/vacancy/40700178","working_days":[],"working_time_intervals":[],"working_time_modes":[],"accept_temporary":false}